README
setup.cfg
setup.py
logpp/__init__.py
logpp/logging.py
logpp/version.py
logpp.egg-info/PKG-INFO
logpp.egg-info/SOURCES.txt
logpp.egg-info/dependency_links.txt
logpp.egg-info/top_level.txt