Metadata-Version: 1.2
Name: logpp
Version: 0.0.8
Summary: python logging extensions
Home-page: http://logpp.readthedocs.io/en/latest/index.html
Author: Pat Daburu
Author-email: pat@daburu.net
License: MIT
Download-URL: https://github.com/patdaburu/logpp/archive/0.0.8.tar.gz
Platform: UNKNOWN
Classifier: Development Status :: 3 - Alpha
Classifier: Intended Audience :: Developers
Classifier: Topic :: Software Development :: Libraries
Classifier: License :: OSI Approved :: MIT License
Classifier: Programming Language :: Python :: 3.6
Requires-Python: >=3.6
